aryn_sdk/__init__.py
aryn_sdk/client/__init__.py
aryn_sdk/client/art.py
aryn_sdk/client/client.py
aryn_sdk/client/config.py
aryn_sdk/client/exceptions.py
aryn_sdk/client/helpers.py
aryn_sdk/client/partition.py
aryn_sdk/client/response.py
aryn_sdk/client/tasks.py
aryn_sdk/partition/__init__.py
aryn_sdk/test/__init__.py
aryn_sdk/test/resources/.DS_Store
aryn_sdk/test/resources/image/jpeg_bytes.jpeg
aryn_sdk/test/resources/image/partitioning_output.json
aryn_sdk/test/resources/image/pngb64str.txt
aryn_sdk/test/resources/image/unsupported-format-test-document-image.heic
aryn_sdk/test/resources/json/3m_output.json
aryn_sdk/test/resources/json/3m_output_ocr.json
aryn_sdk/test/resources/json/3m_output_ocr_table.json
aryn_sdk/test/resources/json/3m_output_table.json
aryn_sdk/test/resources/json/SPsort_output.json
aryn_sdk/test/resources/json/SPsort_output_images.json
aryn_sdk/test/resources/json/SPsort_output_images_page0.json
aryn_sdk/test/resources/json/SPsort_output_images_page1.json
aryn_sdk/test/resources/json/rotated.json
aryn_sdk/test/resources/pdfs/3m_table.pdf
aryn_sdk/test/resources/pdfs/FR-2002-05-03-TRUNCATED-40.pdf
aryn_sdk/test/resources/pdfs/SPsort.pdf
aryn_sdk/test/resources/pdfs/rotated.pdf
aryn_sdk/test/test_partition.py
aryn_sdk/types/_schema.py
aryn_sdk/types/async.py
aryn_sdk/types/connection.py
aryn_sdk/types/docset.py
aryn_sdk/types/document.py
aryn_sdk/types/parse.py
aryn_sdk/types/prompt.py
aryn_sdk/types/query.py
aryn_sdk/types/schema.py
aryn_sdk/types/search.py
aryn_sdk/types/task.py
aryn_sdk/types/transforms.py
aryn_sdk-0.2.14.dist-info/METADATA
aryn_sdk-0.2.14.dist-info/WHEEL
aryn_sdk-0.2.14.dist-info/licenses/LICENSE
aryn_sdk-0.2.14.dist-info/RECORD
