Metadata-Version: 2.4
Name: aryn-sdk
Version: 0.2.14
Summary: The client library for Aryn services.
License: Apache 2.0
License-File: LICENSE
Author: aryn.ai
Author-email: opensource@aryn.ai
Requires-Python: >=3.9
Classifier: License :: Other/Proprietary License
Classifier: Programming Language :: Python :: 3
Classifier: Programming Language :: Python :: 3.9
Classifier: Programming Language :: Python :: 3.10
Classifier: Programming Language :: Python :: 3.11
Classifier: Programming Language :: Python :: 3.12
Classifier: Programming Language :: Python :: 3.13
Classifier: Programming Language :: Python :: 3.14
Requires-Dist: httpcore (>=1.0.9)
Requires-Dist: httpx (>=0.25.0,<1)
Requires-Dist: httpx-sse (>=0.4.0,<0.5.0)
Requires-Dist: numpy (>=2.0)
Requires-Dist: packaging (>=24.1,<25.0)
Requires-Dist: pandas (>=2.0)
Requires-Dist: pdf2image (>=1.16.3,<2.0.0)
Requires-Dist: pillow (>=11.1.0)
Requires-Dist: pydantic (>=2.10.6,<3.0.0)
Requires-Dist: pyyaml (>=6.0.1,<7.0.0)
